{
  "items": [
    {
      "name": "ASTRAL CHAIN",
      "link": "https://www.dekudeals.com/items/astral-chain",
      "added_at": "2024-06-10T20:17:25+00:00",
      "format": "digital",
      "price_paid": 43900,
      "price_paid_currency": "NOK"
    },
    {
      "name": "Badland: Game of the Year Edition",
      "link": "https://www.dekudeals.com/items/badland-game-of-the-year-edition",
      "added_at": "2025-06-01T22:24:39+00:00",
      "format": "digital",
      "price_paid": 1400,
      "price_paid_currency": "NOK"
    },
    {
      "name": "Batman: The Enemy Within",
      "link": "https://www.dekudeals.com/items/batman-the-enemy-within",
      "added_at": "2024-06-22T11:53:43+00:00",
      "status": "completed",
      "format": "digital",
      "price_paid": 6100,
      "price_paid_currency": "NOK"
    },
    {
      "name": "Batman - The Telltale Series",
      "link": "https://www.dekudeals.com/items/batman-the-telltale-series",
      "added_at": "2024-02-13T20:06:58+00:00",
      "status": "completed",
      "format": "digital",
      "price_paid": 6100,
      "price_paid_currency": "NOK"
    },
    {
      "name": "Big Brain Academy: Brain vs. Brain",
      "link": "https://www.dekudeals.com/items/big-brain-academy-brain-vs-brain",
      "added_at": "2025-01-01T18:24:48+00:00",
      "format": "digital",
      "price_paid": 21900,
      "price_paid_currency": "NOK"
    },
    {
      "name": "Brothers: A Tale of Two Sons",
      "link": "https://www.dekudeals.com/items/brothers-a-tale-of-two-sons",
      "added_at": "2024-02-13T20:13:59+00:00",
      "format": "digital",
      "price_paid": 2800,
      "price_paid_currency": "NOK"
    },
    {
      "name": "Burnout Paradise Remastered",
      "link": "https://www.dekudeals.com/items/burnout-paradise-remastered",
      "added_at": "2024-02-13T20:03:51+00:00",
      "status": "completed",
      "format": "digital",
      "price_paid": 5900,
      "price_paid_currency": "NOK",
      "note": "20"
    },
    {
      "name": "Captain Toad: Treasure Tracker and Captain Toad: Treasure Tracker - Special Episode Bundle",
      "link": "https://www.dekudeals.com/items/captain-toad-treasure-tracker-and-captain-toad-treasure-tracker-special-episode-bundle",
      "added_at": "2025-07-24T19:27:45+00:00",
      "format": "digital",
      "price_paid": 35300,
      "price_paid_currency": "NOK"
    },
    {
      "name": "Chants of Sennaar",
      "link": "https://www.dekudeals.com/items/chants-of-sennaar",
      "added_at": "2024-04-19T14:06:04+00:00",
      "status": "completed",
      "format": "digital",
      "price_paid": 14900,
      "price_paid_currency": "NOK",
      "note": "5"
    },
    {
      "name": "Chicory: A Colorful Tale",
      "link": "https://www.dekudeals.com/items/chicory-a-colorful-tale",
      "added_at": "2024-06-10T20:18:21+00:00",
      "format": "digital",
      "price_paid": 9500,
      "price_paid_currency": "NOK"
    },
    {
      "name": "DAVE THE DIVER",
      "link": "https://www.dekudeals.com/items/dave-the-diver",
      "added_at": "2025-11-22T10:54:06+00:00",
      "format": "digital",
      "price_paid": 12000,
      "price_paid_currency": "NOK"
    },
    {
      "name": "Dead Cells",
      "link": "https://www.dekudeals.com/items/dead-cells",
      "added_at": "2025-03-27T22:44:31+00:00",
      "format": "digital",
      "price_paid": 0,
      "price_paid_currency": "NOK"
    },
    {
      "name": "Dead Cells: Medley of Pain Bundle",
      "link": "https://www.dekudeals.com/items/dead-cells-medley-of-pain-bundle",
      "added_at": "2025-03-27T22:43:34+00:00",
      "format": "digital",
      "price_paid": 7000,
      "price_paid_currency": "NOK",
      "note": "50"
    },
    {
      "name": "Disco Elysium - The Final Cut",
      "link": "https://www.dekudeals.com/items/disco-elysium-the-final-cut",
      "added_at": "2024-02-13T19:57:44+00:00",
      "format": "digital",
      "price_paid": 12000,
      "price_paid_currency": "NOK"
    },
    {
      "name": "Divinity: Original Sin 2 - Definitive Edition",
      "link": "https://www.dekudeals.com/items/divinity-original-sin-2-definitive-edition",
      "added_at": "2025-12-19T22:32:44+00:00",
      "format": "digital",
      "price_paid": 25000,
      "price_paid_currency": "NOK"
    },
    {
      "name": "Door Kickers",
      "link": "https://www.dekudeals.com/items/door-kickers",
      "added_at": "2024-02-13T20:13:42+00:00",
      "format": "digital",
      "price_paid": 1000,
      "price_paid_currency": "NOK"
    },
    {
      "name": "DYSMANTLE",
      "link": "https://www.dekudeals.com/items/dysmantle",
      "added_at": "2025-07-24T19:29:40+00:00",
      "status": "completed",
      "format": "digital",
      "price_paid": 8000,
      "price_paid_currency": "NOK",
      "note": "40"
    },
    {
      "name": "FAR: Changing Tides",
      "link": "https://www.dekudeals.com/items/far-changing-tides",
      "added_at": "2025-07-17T19:42:10+00:00",
      "format": "digital",
      "price_paid": 5900,
      "price_paid_currency": "NOK"
    },
    {
      "name": "FAR: Lone Sails",
      "link": "https://www.dekudeals.com/items/far-lone-sails",
      "added_at": "2024-02-13T19:57:00+00:00",
      "status": "completed",
      "format": "digital",
      "price_paid": 1500,
      "price_paid_currency": "NOK"
    },
    {
      "name": "GRID Autosport",
      "link": "https://www.dekudeals.com/items/grid-autosport",
      "added_at": "2025-12-19T22:28:51+00:00",
      "format": "digital",
      "price_paid": 15900,
      "price_paid_currency": "NOK"
    },
    {
      "name": "Hades",
      "link": "https://www.dekudeals.com/items/hades",
      "added_at": "2024-06-27T16:02:11+00:00",
      "format": "digital",
      "price_paid": 10000,
      "price_paid_currency": "NOK"
    },
    {
      "name": "Hogwarts Legacy: Deluxe Edition",
      "link": "https://www.dekudeals.com/items/hogwarts-legacy-digital-deluxe-edition",
      "added_at": "2025-11-22T10:53:45+00:00",
      "format": "digital",
      "price_paid": 11200,
      "price_paid_currency": "NOK"
    },
    {
      "name": "Hollow Knight",
      "link": "https://www.dekudeals.com/items/hollow-knight",
      "added_at": "2024-04-19T14:05:40+00:00",
      "format": "digital",
      "price_paid": 5000,
      "price_paid_currency": "NOK"
    },
    {
      "name": "Immortals Fenyx Rising",
      "link": "https://www.dekudeals.com/items/immortals-fenyx-rising",
      "added_at": "2025-06-01T21:45:46+00:00",
      "format": "digital",
      "price_paid": 8900,
      "price_paid_currency": "NOK"
    },
    {
      "name": "INSIDE",
      "link": "https://www.dekudeals.com/items/inside",
      "added_at": "2024-02-13T19:53:45+00:00",
      "status": "completed",
      "format": "digital",
      "price_paid": 2200,
      "price_paid_currency": "NOK"
    },
    {
      "name": "Into the Breach",
      "link": "https://www.dekudeals.com/items/into-the-breach",
      "added_at": "2024-04-19T14:05:28+00:00",
      "format": "digital",
      "price_paid": 5100,
      "price_paid_currency": "NOK",
      "note": "40"
    },
    {
      "name": "The Legend of Zelda: Breath of the Wild",
      "link": "https://www.dekudeals.com/items/the-legend-of-zelda-breath-of-the-wild",
      "added_at": "2024-02-13T19:55:16+00:00",
      "status": "completed",
      "format": "physical",
      "price_paid": 60000,
      "price_paid_currency": "NOK",
      "note": "70"
    },
    {
      "name": "The Legend of Zelda: Breath of the Wild Expansion Pass",
      "link": "https://www.dekudeals.com/items/the-legend-of-zelda-breath-of-the-wild-expansion-pass",
      "added_at": "2024-06-10T20:21:10+00:00",
      "format": "digital",
      "price_paid": 9800,
      "price_paid_currency": "NOK"
    },
    {
      "name": "The Legend of Zelda: Echoes of Wisdom",
      "link": "https://www.dekudeals.com/items/the-legend-of-zelda-echoes-of-wisdom",
      "added_at": "2024-07-05T10:38:41+00:00",
      "status": "completed",
      "format": "digital",
      "price_paid": 54500,
      "price_paid_currency": "NOK",
      "note": "25"
    },
    {
      "name": "The Legend of Zelda: Link’s Awakening",
      "link": "https://www.dekudeals.com/items/the-legend-of-zelda-links-awakening",
      "added_at": "2024-02-13T20:13:12+00:00",
      "status": "completed",
      "format": "physical",
      "price_paid": 55000,
      "price_paid_currency": "NOK",
      "note": "15"
    },
    {
      "name": "The Legend of Zelda: Tears of the Kingdom",
      "link": "https://www.dekudeals.com/items/the-legend-of-zelda-tears-of-the-kingdom",
      "added_at": "2024-02-13T19:55:19+00:00",
      "status": "completed",
      "format": "physical",
      "price_paid": 65000,
      "price_paid_currency": "NOK",
      "note": "145"
    },
    {
      "name": "LEGO Bricktales",
      "link": "https://www.dekudeals.com/items/lego-bricktales-switch",
      "added_at": "2025-04-26T10:26:49+00:00",
      "format": "digital",
      "price_paid": 6000,
      "price_paid_currency": "NOK"
    },
    {
      "name": "LEGO Builder's Journey",
      "link": "https://www.dekudeals.com/items/lego-builders-journey",
      "added_at": "2025-04-26T10:27:02+00:00",
      "format": "digital",
      "price_paid": 5000,
      "price_paid_currency": "NOK"
    },
    {
      "name": "LEGO CITY Undercover",
      "link": "https://www.dekudeals.com/items/lego-city-undercover",
      "added_at": "2024-10-07T15:38:21+00:00",
      "status": "completed",
      "format": "digital",
      "price_paid": 4900,
      "price_paid_currency": "NOK",
      "note": "10"
    },
    {
      "name": "LEGO DC Super-Villains Deluxe Edition",
      "link": "https://www.dekudeals.com/items/lego-dc-super-villains-deluxe",
      "added_at": "2025-04-26T10:30:56+00:00",
      "status": "completed",
      "format": "digital",
      "price_paid": 5100,
      "price_paid_currency": "NOK",
      "note": "15"
    },
    {
      "name": "LEGO Marvel Super Heroes",
      "link": "https://www.dekudeals.com/items/lego-marvel-super-heroes",
      "added_at": "2025-03-25T21:52:03+00:00",
      "status": "completed",
      "format": "digital",
      "price_paid": 4100,
      "price_paid_currency": "NOK",
      "note": "10"
    },
    {
      "name": "LEGO Marvel Super Heroes 2",
      "link": "https://www.dekudeals.com/items/lego-marvel-super-heroes-2",
      "added_at": "2025-11-22T10:53:56+00:00",
      "status": "completed",
      "format": "digital",
      "price_paid": 4900,
      "price_paid_currency": "NOK"
    },
    {
      "name": "LEGO Star Wars: The Skywalker Saga",
      "link": "https://www.dekudeals.com/items/lego-star-wars-the-skywalker-saga",
      "added_at": "2024-05-08T19:51:53+00:00",
      "status": "completed",
      "format": "digital",
      "price_paid": 14900,
      "price_paid_currency": "NOK",
      "note": "15"
    },
    {
      "name": "LEGO Worlds",
      "link": "https://www.dekudeals.com/items/lego-worlds",
      "added_at": "2025-04-20T18:47:10+00:00",
      "format": "digital",
      "price_paid": 3400,
      "price_paid_currency": "NOK"
    },
    {
      "name": "LIMBO",
      "link": "https://www.dekudeals.com/items/limbo",
      "added_at": "2024-02-13T19:53:54+00:00",
      "format": "digital",
      "price_paid": 1100,
      "price_paid_currency": "NOK"
    },
    {
      "name": "Linelight",
      "link": "https://www.dekudeals.com/items/linelight",
      "added_at": "2025-09-17T21:27:30+00:00",
      "format": "digital",
      "price_paid": 2000,
      "price_paid_currency": "NOK"
    },
    {
      "name": "Mario + Rabbids Kingdom Battle",
      "link": "https://www.dekudeals.com/items/mario-rabbids-kingdom-battle",
      "added_at": "2024-02-13T19:58:28+00:00",
      "status": "completed",
      "format": "digital",
      "price_paid": 13200,
      "price_paid_currency": "NOK",
      "note": "25"
    },
    {
      "name": "Mario + Rabbids Kingdom Battle Donkey Kong Adventure",
      "link": "https://www.dekudeals.com/items/donkey-kong-adventure",
      "added_at": "2025-01-25T00:19:26+00:00",
      "status": "completed",
      "format": "digital",
      "price_paid": 5900,
      "price_paid_currency": "NOK"
    },
    {
      "name": "Mario + Rabbids Sparks of Hope",
      "link": "https://www.dekudeals.com/items/mario-plus-rabbids-sparks-of-hope",
      "added_at": "2024-04-05T21:52:18+00:00",
      "status": "completed",
      "format": "digital",
      "price_paid": 19700,
      "price_paid_currency": "NOK",
      "note": "30"
    },
    {
      "name": "Mario vs. Donkey Kong",
      "link": "https://www.dekudeals.com/items/mario-vs-donkey-kong",
      "added_at": "2025-06-28T17:22:12+00:00",
      "format": "physical",
      "price_paid": 55500,
      "price_paid_currency": "NOK",
      "note": "7"
    },
    {
      "name": "Metroid Dread",
      "link": "https://www.dekudeals.com/items/metroid-dread",
      "added_at": "2024-06-22T11:52:02+00:00",
      "format": "digital",
      "price_paid": 43900,
      "price_paid_currency": "NOK"
    },
    {
      "name": "Monster Boy and the Cursed Kingdom",
      "link": "https://www.dekudeals.com/items/monster-boy-and-the-cursed-kingdom",
      "added_at": "2024-02-13T19:57:58+00:00",
      "format": "digital",
      "price_paid": 8000,
      "price_paid_currency": "NOK"
    },
    {
      "name": "Monument Valley: The Collection",
      "link": "https://www.dekudeals.com/items/monument-valley-panoramic-collection",
      "added_at": "2025-11-20T22:29:50+00:00",
      "format": "digital",
      "price_paid": 24600,
      "price_paid_currency": "NOK"
    },
    {
      "name": "Moonlighter",
      "link": "https://www.dekudeals.com/items/moonlighter",
      "added_at": "2024-02-13T19:59:39+00:00",
      "status": "completed",
      "format": "digital",
      "price_paid": 2400,
      "price_paid_currency": "NOK",
      "note": "15"
    },
    {
      "name": "Need for Speed Hot Pursuit Remastered",
      "link": "https://www.dekudeals.com/items/need-for-speed-hot-pursuit-remastered",
      "added_at": "2024-03-29T22:41:57+00:00",
      "format": "digital",
      "price_paid": 7900,
      "price_paid_currency": "NOK"
    },
    {
      "name": "NieR:Automata The End of YoRHa Edition",
      "link": "https://www.dekudeals.com/items/nier-automata-the-end-of-yorha-edition-switch",
      "added_at": "2024-09-19T21:41:04+00:00",
      "format": "digital",
      "price_paid": 19900,
      "price_paid_currency": "NOK"
    },
    {
      "name": "No Man's Sky",
      "link": "https://www.dekudeals.com/items/no-mans-sky",
      "added_at": "2024-07-20T22:08:09+00:00",
      "format": "digital",
      "price_paid": 0,
      "price_paid_currency": "NOK",
      "note": "100"
    },
    {
      "name": "Ori and the Blind Forest: Definitive Edition",
      "link": "https://www.dekudeals.com/items/ori-and-the-blind-forest-de",
      "added_at": "2024-03-15T21:35:27+00:00",
      "format": "digital",
      "price_paid": 6500,
      "price_paid_currency": "NOK"
    },
    {
      "name": "Outer Wilds",
      "link": "https://www.dekudeals.com/items/outer-wilds",
      "added_at": "2025-10-17T22:05:33+00:00",
      "format": "digital",
      "price_paid": 15000,
      "price_paid_currency": "NOK"
    },
    {
      "name": "The Pedestrian",
      "link": "https://www.dekudeals.com/items/the-pedestrian",
      "added_at": "2024-04-19T14:05:53+00:00",
      "status": "completed",
      "format": "digital",
      "price_paid": 10900,
      "price_paid_currency": "NOK"
    },
    {
      "name": "Pokémon Legends: Arceus",
      "link": "https://www.dekudeals.com/items/pokemon-legends-arceus",
      "added_at": "2025-08-17T20:23:34+00:00",
      "status": "completed",
      "format": "physical",
      "price_paid": 46900,
      "price_paid_currency": "NOK",
      "note": "40"
    },
    {
      "name": "Prince of Persia The Lost Crown",
      "link": "https://www.dekudeals.com/items/prince-of-persia-the-lost-crown",
      "added_at": "2024-12-18T21:23:42+00:00",
      "format": "digital",
      "price_paid": 22400,
      "price_paid_currency": "NOK"
    },
    {
      "name": "Red Dead Redemption",
      "link": "https://www.dekudeals.com/items/red-dead-redemption",
      "added_at": "2025-12-19T22:31:11+00:00",
      "format": "digital",
      "price_paid": 27400,
      "price_paid_currency": "NOK"
    },
    {
      "name": "RUINER",
      "link": "https://www.dekudeals.com/items/ruiner",
      "added_at": "2024-04-05T22:00:28+00:00",
      "status": "completed",
      "format": "digital",
      "price_paid": 800,
      "price_paid_currency": "NOK"
    },
    {
      "name": "Scott Pilgrim vs. The World: The Game – Complete Edition",
      "link": "https://www.dekudeals.com/items/scott-pilgrim-vs-the-world-the-game-complete-edition",
      "added_at": "2025-06-01T22:22:12+00:00",
      "format": "digital"
    },
    {
      "name": "Sky: Children of the Light",
      "link": "https://www.dekudeals.com/items/sky-children-of-the-light",
      "added_at": "2024-02-13T20:00:33+00:00",
      "format": "digital"
    },
    {
      "name": "SnowRunner",
      "link": "https://www.dekudeals.com/items/snowrunner",
      "added_at": "2024-02-13T20:12:56+00:00",
      "format": "digital",
      "price_paid": 19900,
      "price_paid_currency": "NOK",
      "note": "530"
    },
    {
      "name": "SnowRunner - Jack of All Treads Tire Pack",
      "link": "https://www.dekudeals.com/items/snowrunner-jack-of-all-treads-tire-pack",
      "added_at": "2024-04-16T21:56:26+00:00",
      "format": "digital",
      "price_paid": 3300,
      "price_paid_currency": "NOK"
    },
    {
      "name": "SnowRunner - The Mastodon",
      "link": "https://www.dekudeals.com/items/snowrunner-the-mastodon",
      "added_at": "2024-03-24T15:45:03+00:00",
      "format": "digital",
      "price_paid": 3900,
      "price_paid_currency": "NOK"
    },
    {
      "name": "SnowRunner - Year 1 Pass + Year 2 Pass + Year 3 Pass",
      "link": "https://www.dekudeals.com/items/snowrunner-year-1-pass-plus-year-2-pass-plus-year-3-pass",
      "added_at": "2024-03-24T15:43:22+00:00",
      "format": "digital",
      "price_paid": 52400,
      "price_paid_currency": "NOK"
    },
    {
      "name": "Spaceland",
      "link": "https://www.dekudeals.com/items/spaceland",
      "added_at": "2025-02-20T18:05:43+00:00",
      "format": "digital",
      "price_paid": 4000,
      "price_paid_currency": "NOK"
    },
    {
      "name": "Stardew Valley",
      "link": "https://www.dekudeals.com/items/stardew-valley",
      "added_at": "2024-02-26T23:01:01+00:00",
      "format": "digital",
      "price_paid": 5000,
      "price_paid_currency": "NOK"
    },
    {
      "name": "SteamWorld Dig",
      "link": "https://www.dekudeals.com/items/steamworld-dig",
      "added_at": "2025-02-04T16:37:07+00:00",
      "status": "completed",
      "format": "digital",
      "price_paid": 1000,
      "price_paid_currency": "NOK",
      "note": "7"
    },
    {
      "name": "SteamWorld Dig 2",
      "link": "https://www.dekudeals.com/items/steamworld-dig-2",
      "added_at": "2025-04-02T15:25:53+00:00",
      "format": "digital",
      "price_paid": 1600,
      "price_paid_currency": "NOK"
    },
    {
      "name": "SteamWorld Heist II",
      "link": "https://www.dekudeals.com/items/steamworld-heist-2",
      "added_at": "2025-06-01T21:43:01+00:00",
      "status": "completed",
      "price_paid": 16400,
      "price_paid_currency": "NOK",
      "note": "30"
    },
    {
      "name": "SteamWorld Heist: Ultimate Edition",
      "link": "https://www.dekudeals.com/items/steamworld-heist-ultimate-edition",
      "added_at": "2024-02-28T21:10:39+00:00",
      "status": "completed",
      "format": "digital",
      "price_paid": 0,
      "price_paid_currency": "NOK",
      "note": "15"
    },
    {
      "name": "SteamWorld Quest: Hand of Gilgamech",
      "link": "https://www.dekudeals.com/items/steamworld-quest",
      "added_at": "2025-02-04T16:37:21+00:00",
      "format": "digital",
      "price_paid": 2300,
      "price_paid_currency": "NOK"
    },
    {
      "name": "Super Mario 3D World + Bowser’s Fury",
      "link": "https://www.dekudeals.com/items/super-mario-3d-world-plus-bowsers-fury",
      "added_at": "2025-06-18T15:03:19+00:00",
      "format": "physical",
      "price_paid": 64000,
      "price_paid_currency": "NOK",
      "note": "10"
    },
    {
      "name": "Super Mario Bros. Wonder",
      "link": "https://www.dekudeals.com/items/super-mario-bros-wonder",
      "added_at": "2024-07-05T10:38:17+00:00",
      "status": "completed",
      "format": "digital",
      "price_paid": 54500,
      "price_paid_currency": "NOK",
      "note": "10"
    },
    {
      "name": "Super Mario Galaxy + Super Mario Galaxy 2",
      "link": "https://www.dekudeals.com/items/super-mario-galaxy-and-super-mario-galaxy-2",
      "added_at": "2025-11-22T10:54:56+00:00",
      "format": "physical",
      "price_paid": 70500,
      "price_paid_currency": "NOK"
    },
    {
      "name": "Super Mario Odyssey",
      "link": "https://www.dekudeals.com/items/super-mario-odyssey",
      "added_at": "2024-02-13T19:55:13+00:00",
      "status": "completed",
      "format": "physical",
      "price_paid": 55000,
      "price_paid_currency": "NOK",
      "note": "5"
    },
    {
      "name": "Teenage Mutant Ninja Turtles: Shredder's Revenge",
      "link": "https://www.dekudeals.com/items/teenage-mutant-ninja-turtles-shredders-revenge",
      "added_at": "2024-04-05T21:56:58+00:00",
      "status": "completed",
      "format": "digital",
      "price_paid": 16600,
      "price_paid_currency": "NOK"
    },
    {
      "name": "Teenage Mutant Ninja Turtles: Splintered Fate",
      "link": "https://www.dekudeals.com/items/tmnt-splintered-fate",
      "added_at": "2025-10-05T21:01:32+00:00",
      "format": "digital",
      "price_paid": 16400,
      "price_paid_currency": "NOK"
    },
    {
      "name": "Teenage Mutant Ninja Turtles: The Cowabunga Collection",
      "link": "https://www.dekudeals.com/items/teenage-mutant-ninja-turtles-the-cowabunga-collection",
      "added_at": "2024-03-06T00:13:46+00:00",
      "format": "digital",
      "price_paid": 24000,
      "price_paid_currency": "NOK"
    },
    {
      "name": "Tents and Trees",
      "link": "https://www.dekudeals.com/items/tents-and-trees",
      "added_at": "2025-12-19T22:27:43+00:00",
      "format": "digital",
      "price_paid": 2000,
      "price_paid_currency": "NOK"
    },
    {
      "name": "Tony Hawk's Pro Skater 1 + 2",
      "link": "https://www.dekudeals.com/items/tony-hawks-pro-skater-1-plus-2",
      "added_at": "2024-02-13T19:58:18+00:00",
      "format": "digital",
      "price_paid": 15100,
      "price_paid_currency": "NOK"
    },
    {
      "name": "Warframe",
      "link": "https://www.dekudeals.com/items/warframe",
      "added_at": "2024-02-13T19:58:08+00:00",
      "format": "digital"
    },
    {
      "name": "Warhammer 40,000: Mechanicus",
      "link": "https://www.dekudeals.com/items/warhammer-40000-mechanicus",
      "added_at": "2024-02-13T20:05:50+00:00",
      "format": "digital",
      "price_paid": 10000,
      "price_paid_currency": "NOK"
    },
    {
      "name": "The Witcher 3: Wild Hunt — Complete Edition",
      "link": "https://www.dekudeals.com/items/the-witcher-3-wild-hunt-complete-edition",
      "added_at": "2024-12-18T21:23:50+00:00",
      "format": "digital",
      "price_paid": 18100,
      "price_paid_currency": "NOK"
    },
    {
      "name": "World of Goo 2",
      "link": "https://www.dekudeals.com/items/world-of-goo-2",
      "added_at": "2025-11-22T10:53:23+00:00",
      "format": "digital",
      "price_paid": 23100,
      "price_paid_currency": "NOK"
    },
    {
      "name": "Wreckfest",
      "link": "https://www.dekudeals.com/items/wreckfest",
      "added_at": "2024-08-10T18:00:57+00:00",
      "status": "completed",
      "format": "digital",
      "price_paid": 17200,
      "price_paid_currency": "NOK",
      "note": "10"
    },
    {
      "name": "XCOM 2 Collection",
      "link": "https://www.dekudeals.com/items/xcom-2-collection",
      "added_at": "2024-02-13T20:05:36+00:00",
      "status": "completed",
      "price_paid": 7400,
      "price_paid_currency": "NOK"
    }
  ]
}
